pylumber/__init__.py
pylumber/format.py
pylumber-0.1.2.dist-info/LICENSE
pylumber-0.1.2.dist-info/METADATA
pylumber-0.1.2.dist-info/WHEEL
pylumber-0.1.2.dist-info/top_level.txt
pylumber-0.1.2.dist-info/RECORD
